{"Added":[],"Modified":[{"Id":60104,"Kind":10,"Name":"User Employee Mapping","Namespace":""},{"Id":60104,"Kind":12,"Name":"User Employee Mapping","Namespace":""},{"Id":60100,"Kind":26,"Name":"Absence","Namespace":""},{"Id":60103,"Kind":12,"Name":"Leave Entry","Namespace":""},{"Id":60102,"Kind":12,"Name":"Leave Entitlement","Namespace":""},{"Id":60102,"Kind":10,"Name":"Leave Entitlement","Namespace":""},{"Id":60101,"Kind":12,"Name":"Leave Request","Namespace":""},{"Id":60100,"Kind":12,"Name":"Leave Type","Namespace":""},{"Id":60101,"Kind":10,"Name":"Leave Request","Namespace":""}],"Removed":[]}